{
  "ProgressEvent": {
    "props": {
      "prototype": {
        "props": {
          "total": {
            "kind": "v",
            "type": "Number",
            "menu": "total : Number"
          },
          "loaded": {
            "kind": "v",
            "type": "Number",
            "menu": "loaded : Number"
          },
          "lengthComputable": {
            "kind": "v",
            "type": "Boolean",
            "menu": "lengthComputable : Boolean"
          }
        },
        "class": "ProgressEvent",
        "type": "Object",
        "kind": "v"
      }
    },
    "type": "ProgressEvent",
    "menu": "new ProgressEvent(type : String, [args : Object]) : ProgressEvent",
    "kind": "f"
  },
  "HTMLUListElement": {
    "kind": "v"
  },
  "HTMLLinkElement": {
    "kind": "f",
    "props": {
      "prototype": {
        "props": {
          "type": {
            "kind": "v",
            "type": "String",
            "menu": "type : String"
          },
          "sizes": {
            "kind": "v",
            "type": "DOMSettableTokenList",
            "menu": "sizes : DOMSettableTokenList readonly"
          },
          "relList": {
            "kind": "v",
            "type": "DOMTokenList",
            "menu": "relList : DOMTokenList readonly"
          },
          "rel": {
            "kind": "v",
            "type": "String",
            "menu": "rel : String"
          },
          "media": {
            "kind": "v",
            "type": "String",
            "menu": "media : String"
          },
          "hreflang": {
            "kind": "v",
            "type": "String",
            "menu": "hreflang : String"
          },
          "href": {
            "kind": "v",
            "type": "String",
            "menu": "href : String"
          },
          "disabled": {
            "kind": "v",
            "type": "Boolean",
            "menu": "disabled : Boolean"
          }
        },
        "class": "HTMLLinkElement",
        "type": "Object",
        "kind": "v"
      }
    }
  },
  "FormData": {
    "props": {
      "prototype": {
        "props": {},
        "class": "FormData",
        "type": "Object",
        "kind": "v"
      }
    },
    "type": "FormData",
    "menu": "new FormData(form : HTMLFormElement) : FormData",
    "kind": "f"
  },
  "XMLSerializer": {
    "props": {
      "prototype": {
        "props": {
          "serializeToString": {
            "kind": "f",
            "type": "String",
            "menu": "serializeToString(root : Node) : String"
          }
        },
        "class": "XMLSerializer",
        "type": "Object",
        "kind": "v"
      }
    },
    "type": "XMLSerializer",
    "menu": "new XMLSerializer() : XMLSerializer",
    "kind": "f"
  },
  "MouseEvent": {
    "props": {
      "prototype": {
        "props": {
          "screenX": {
            "kind": "v",
            "type": "Number",
            "menu": "screenX : Number readonly"
          },
          "relatedTarget": {
            "kind": "v",
            "type": "Element",
            "menu": "relatedTarget : Element readonly"
          },
          "pageY": {
            "kind": "v",
            "type": "Number",
            "menu": "pageY : Number readonly"
          },
          "offsetX": {
            "kind": "v",
            "type": "Number",
            "menu": "offsetX : Number readonly"
          },
          "metaKey": {
            "kind": "v",
            "type": "Boolean",
            "menu": "metaKey : Boolean readonly"
          },
          "ctrlKey": {
            "kind": "v",
            "type": "Boolean",
            "menu": "ctrlKey : Boolean readonly"
          },
          "clientY": {
            "kind": "v",
            "type": "Number",
            "menu": "clientY : Number readonly"
          },
          "clientX": {
            "kind": "v",
            "type": "Number",
            "menu": "clientX : Number readonly"
          },
          "screenY": {
            "kind": "v",
            "type": "Number",
            "menu": "screenY : Number readonly"
          },
          "shiftKey": {
            "kind": "v",
            "type": "Boolean",
            "menu": "shiftKey : Boolean readonly"
          },
          "x": {
            "kind": "v",
            "type": "Number",
            "menu": "x : Number readonly"
          },
          "y": {
            "kind": "v",
            "type": "Number",
            "menu": "y : Number readonly"
          },
          "getModifierState": {
            "kind": "f",
            "type": "Boolean",
            "menu": "getModifierState(keyArg : String) : Boolean"
          },
          "initMouseEvent": {
            "kind": "f",
            "type": "undefined",
            "menu": "initMouseEvent(type : String, bubbles : Boolean, cancelable : Boolean, view : Window, detail : Number, screenX : Number, screenY : Number, clientX : Number, clientY : Number, ctrlKey : Boolean, altKey : Boolean, shiftKey : Boolean, metaKey : Boolean, button : Number, [relatedTarget : Element]) : undefined"
          },
          "buttons": {
            "kind": "v",
            "type": "Number",
            "menu": "buttons : Number readonly"
          },
          "button": {
            "kind": "v",
            "type": "Number",
            "menu": "button : Number readonly"
          },
          "altKey": {
            "kind": "v",
            "type": "Boolean",
            "menu": "altKey : Boolean readonly"
          },
          "offsetY": {
            "kind": "v",
            "type": "Number",
            "menu": "offsetY : Number readonly"
          },
          "pageX": {
            "kind": "v",
            "type": "Number",
            "menu": "pageX : Number readonly"
          }
        },
        "class": "MouseEvent",
        "type": "Object",
        "kind": "v"
      }
    },
    "type": "MouseEvent",
    "menu": "new MouseEvent(type : String, [eventInit : Object]) : MouseEvent",
    "kind": "f"
  },
  "HTMLHtmlElement": {
    "kind": "v"
  },
  "DOMStringMap": {
    "kind": "v"
  },
  "HTMLImageElement": {
    "kind": "f",
    "props": {
      "prototype": {
        "props": {
          "width": {
            "kind": "v",
            "type": "Number",
            "menu": "width : Number"
          },
          "src": {
            "kind": "v",
            "type": "String",
            "menu": "src : String"
          },
          "naturalWidth": {
            "kind": "v",
            "type": "Number",
            "menu": "naturalWidth : Number readonly"
          },
          "naturalHeight": {
            "kind": "v",
            "type": "Number",
            "menu": "naturalHeight : Number readonly"
          },
          "height": {
            "kind": "v",
            "type": "Number",
            "menu": "height : Number"
          },
          "complete": {
            "kind": "v",
            "type": "Boolean",
            "menu": "complete : Boolean"
          },
          "alt": {
            "kind": "v",
            "type": "String",
            "menu": "alt : String"
          }
        },
        "class": "HTMLImageElement",
        "type": "Object",
        "kind": "v"
      }
    }
  },
  "DocumentType": {
    "kind": "v"
  },
  "ProcessingInstruction": {
    "kind": "v"
  },
  "HTMLQuoteElement": {
    "kind": "f",
    "props": {
      "prototype": {
        "props": {
          "cite": {
            "kind": "v",
            "type": "String",
            "menu": "cite : String"
          }
        },
        "class": "HTMLQuoteElement",
        "type": "Object",
        "kind": "v"
      }
    }
  },
  "ClientRect": {
    "kind": "f",
    "props": {
      "prototype": {
        "props": {
          "width": {
            "kind": "v",
            "type": "Number",
            "menu": "width : Number"
          },
          "top": {
            "kind": "v",
            "type": "Number",
            "menu": "top : Number"
          },
          "right": {
            "kind": "v",
            "type": "Number",
            "menu": "right : Number"
          },
          "left": {
            "kind": "v",
            "type": "Number",
            "menu": "left : Number"
          },
          "height": {
            "kind": "v",
            "type": "Number",
            "menu": "height : Number"
          },
          "bottom": {
            "kind": "v",
            "type": "Number",
            "menu": "bottom : Number"
          }
        },
        "class": "ClientRect",
        "type": "Object",
        "kind": "v"
      }
    }
  },
  "MutationRecord": {
    "kind": "f",
    "props": {
      "prototype": {
        "props": {
          "removedNodes": {
            "kind": "v",
            "type": "NodeList",
            "menu": "removedNodes : NodeList readonly"
          },
          "target": {
            "kind": "v",
            "type": "Node",
            "menu": "target : Node readonly"
          },
          "type": {
            "kind": "v",
            "type": "String",
            "menu": "type : String readonly"
          },
          "addedNodes": {
            "kind": "v",
            "type": "NodeList",
            "menu": "addedNodes : NodeList readonly"
          },
          "attributeName": {
            "kind": "v",
            "type": "String",
            "menu": "attributeName : String readonly"
          },
          "attributeNamespace": {
            "kind": "v",
            "type": "String",
            "menu": "attributeNamespace : String readonly"
          },
          "nextSibling": {
            "kind": "v",
            "type": "Node",
            "menu": "nextSibling : Node readonly"
          },
          "oldValue": {
            "kind": "v",
            "type": "String",
            "menu": "oldValue : String readonly"
          },
          "previousSibling": {
            "kind": "v",
            "type": "Node",
            "menu": "previousSibling : Node readonly"
          }
        },
        "class": "MutationRecord",
        "type": "Object",
        "kind": "v"
      }
    }
  },
  "NodeList": {
    "kind": "f",
    "props": {
      "prototype": {
        "props": {
          "item": {
            "kind": "f",
            "type": "Node",
            "menu": "item(index : Number) : Node"
          },
          "length": {
            "kind": "v",
            "type": "Number",
            "menu": "length : Number readonly"
          }
        },
        "class": "NodeList",
        "type": "Object",
        "kind": "v"
      }
    }
  },
  "HTMLEmbedElement": {
    "kind": "f",
    "props": {
      "prototype": {
        "props": {
          "width": {
            "kind": "v",
            "type": "String",
            "menu": "width : String"
          },
          "type": {
            "kind": "v",
            "type": "String",
            "menu": "type : String"
          },
          "src": {
            "kind": "v",
            "type": "String",
            "menu": "src : String"
          },
          "height": {
            "kind": "v",
            "type": "String",
            "menu": "height : String"
          }
        },
        "class": "HTMLEmbedElement",
        "type": "Object",
        "kind": "v"
      }
    }
  },
  "HTMLIFrameElement": {
    "kind": "f",
    "props": {
      "prototype": {
        "props": {
          "sandbox": {
            "kind": "v",
            "type": "DOMSettableTokenList",
            "menu": "sandbox : DOMSettableTokenList readonly"
          },
          "name": {
            "kind": "v",
            "type": "String",
            "menu": "name : String"
          },
          "src": {
            "kind": "v",
            "type": "String",
            "menu": "src : String"
          },
          "seamless": {
            "kind": "v",
            "type": "Boolean",
            "menu": "seamless : Boolean"
          },
          "width": {
            "kind": "v",
            "type": "String",
            "menu": "width : String"
          },
          "srcdoc": {
            "kind": "v",
            "type": "String",
            "menu": "srcdoc : String"
          },
          "allowFullscreen": {
            "kind": "v",
            "type": "Boolean",
            "menu": "allowFullscreen : Boolean"
          },
          "contentDocument": {
            "kind": "v",
            "type": "Document",
            "menu": "contentDocument : Document readonly"
          },
          "contentWindow": {
            "kind": "v",
            "type": "Window",
            "menu": "contentWindow : Window readonly"
          },
          "height": {
            "kind": "v",
            "type": "String",
            "menu": "height : String"
          }
        },
        "class": "HTMLIFrameElement",
        "type": "Object",
        "kind": "v"
      }
    }
  },
  "DOMImplementation": {
    "kind": "f",
    "props": {
      "prototype": {
        "props": {
          "hasFeature": {
            "kind": "f",
            "type": "Boolean",
            "menu": "hasFeature(feature : String, version : String) : Boolean"
          },
          "createHTMLDocument": {
            "kind": "f",
            "type": "Document",
            "menu": "createHTMLDocument([title : String]) : Document"
          },
          "createDocumentType": {
            "kind": "f",
            "type": "DocumentType",
            "menu": "createDocumentType(qualifiedName : String, publicId : String, systemId : String) : DocumentType"
          },
          "createDocument": {
            "kind": "f",
            "type": "XMLDocument",
            "menu": "createDocument(namespace : String, qualifiedName : String, [documentType : DocumentType]) : XMLDocument"
          },
          "createCSSStyleSheet": {
            "kind": "f",
            "type": "CSSStyleSheet",
            "menu": "createCSSStyleSheet(title : String, media : String) : CSSStyleSheet"
          }
        },
        "class": "DOMImplementation",
        "type": "Object",
        "kind": "v"
      }
    }
  },
  "HTMLLIElement": {
    "kind": "f",
    "props": {
      "prototype": {
        "props": {
          "value": {
            "kind": "v",
            "type": "Number",
            "menu": "value : Number"
          }
        },
        "class": "HTMLLIElement",
        "type": "Object",
        "kind": "v"
      }
    }
  },
  "HTMLButtonElement": {
    "kind": "f",
    "props": {
      "prototype": {
        "props": {
          "willValidate": {
            "kind": "v",
            "type": "Boolean",
            "menu": "willValidate : Boolean readonly"
          },
          "formTarget": {
            "kind": "v",
            "type": "String",
            "menu": "formTarget : String"
          },
          "formNoValidate": {
            "kind": "v",
            "type": "Boolean",
            "menu": "formNoValidate : Boolean"
          },
          "formMethod": {
            "kind": "v",
            "type": "String",
            "menu": "formMethod : String"
          },
          "formEnctype": {
            "kind": "v",
            "type": "String",
            "menu": "formEnctype : String"
          },
          "formAction": {
            "kind": "v",
            "type": "String",
            "menu": "formAction : String"
          },
          "form": {
            "kind": "v",
            "type": "HTMLFormElement",
            "menu": "form : HTMLFormElement readonly"
          },
          "disabled": {
            "kind": "v",
            "type": "Boolean",
            "menu": "disabled : Boolean"
          },
          "checkValidity": {
            "kind": "f",
            "type": "Boolean",
            "menu": "checkValidity() : Boolean"
          },
          "setCustomValidity": {
            "kind": "f",
            "type": "undefined",
            "menu": "setCustomValidity(error : String) : undefined"
          },
          "autofocus": {
            "kind": "v",
            "type": "Boolean",
            "menu": "autofocus : Boolean"
          },
          "labels": {
            "kind": "v",
            "type": "NodeList",
            "menu": "labels : NodeList"
          },
          "name": {
            "kind": "v",
            "type": "String",
            "menu": "name : String"
          },
          "type": {
            "kind": "v",
            "type": "String",
            "menu": "type : String"
          },
          "validationMessage": {
            "kind": "v",
            "type": "String",
            "menu": "validationMessage : String readonly"
          },
          "validity": {
            "kind": "v",
            "type": "ValidityState",
            "menu": "validity : ValidityState readonly"
          },
          "value": {
            "kind": "v",
            "type": "String",
            "menu": "value : String"
          }
        },
        "class": "HTMLButtonElement",
        "type": "Object",
        "kind": "v"
      }
    }
  },
  "StorageEvent": {
    "kind": "f",
    "props": {
      "prototype": {
        "props": {
          "url": {
            "kind": "v",
            "type": "String",
            "menu": "url : String readonly"
          },
          "storageArea": {
            "kind": "v",
            "type": "Storage",
            "menu": "storageArea : Storage readonly"
          },
          "oldValue": {
            "kind": "v",
            "type": "String",
            "menu": "oldValue : String readonly"
          },
          "newValue": {
            "kind": "v",
            "type": "String",
            "menu": "newValue : String readonly"
          },
          "key": {
            "kind": "v",
            "type": "String",
            "menu": "key : String readonly"
          }
        },
        "class": "StorageEvent",
        "type": "Object",
        "kind": "v"
      }
    }
  },
  "HTMLMenuElement": {
    "kind": "v"
  },
  "HTMLBodyElement": {
    "kind": "v"
  },
  "DocumentFragment": {
    "kind": "f",
    "props": {
      "prototype": {
        "props": {
          "querySelectorAll": {
            "kind": "f",
            "type": "NodeList",
            "menu": "querySelectorAll(cssSelector : String) : NodeList"
          },
          "querySelector": {
            "kind": "f",
            "type": "Element",
            "menu": "querySelector(cssSelector : String) : Element"
          }
        },
        "class": "DocumentFragment",
        "type": "Object",
        "kind": "v"
      }
    }
  },
  "HTMLScriptElement": {
    "kind": "f",
    "props": {
      "prototype": {
        "props": {
          "type": {
            "kind": "v",
            "type": "String",
            "menu": "type : String"
          },
          "text": {
            "kind": "v",
            "type": "String",
            "menu": "text : String"
          },
          "src": {
            "kind": "v",
            "type": "String",
            "menu": "src : String"
          },
          "defer": {
            "kind": "v",
            "type": "Boolean",
            "menu": "defer : Boolean"
          },
          "charset": {
            "kind": "v",
            "type": "String",
            "menu": "charset : String"
          },
          "async": {
            "kind": "v",
            "type": "Boolean",
            "menu": "async : Boolean"
          }
        },
        "class": "HTMLScriptElement",
        "type": "Object",
        "kind": "v"
      }
    }
  },
  "Image": {
    "type": "Image",
    "menu": "new Image([width : Number, [height : Number]]) : Image",
    "kind": "f"
  },
  "HTMLBaseElement": {
    "kind": "f",
    "props": {
      "prototype": {
        "props": {
          "target": {
            "kind": "v",
            "type": "String",
            "menu": "target : String"
          },
          "href": {
            "kind": "v",
            "type": "String",
            "menu": "href : String"
          }
        },
        "class": "HTMLBaseElement",
        "type": "Object",
        "kind": "v"
      }
    }
  },
  "Range": {
    "kind": "f",
    "props": {
      "START_TO_START": {
        "kind": "v",
        "type": "Number",
        "menu": "START_TO_START : Number readonly value = 0"
      },
      "START_TO_END": {
        "kind": "v",
        "type": "Number",
        "menu": "START_TO_END : Number readonly value = 1"
      },
      "END_TO_START": {
        "kind": "v",
        "type": "Number",
        "menu": "END_TO_START : Number readonly value = 3"
      },
      "END_TO_END": {
        "kind": "v",
        "type": "Number",
        "menu": "END_TO_END : Number readonly value = 2"
      },
      "prototype": {
        "props": {
          "collapse": {
            "kind": "f",
            "type": "undefined",
            "menu": "collapse(toStart : Boolean) : undefined"
          },
          "collapsed": {
            "kind": "v",
            "type": "Boolean",
            "menu": "collapsed : Boolean readonly"
          },
          "commonAncestorContainer": {
            "kind": "v",
            "type": "Node",
            "menu": "commonAncestorContainer : Node readonly"
          },
          "endContainer": {
            "kind": "v",
            "type": "Node",
            "menu": "endContainer : Node readonly"
          },
          "endOffset": {
            "kind": "v",
            "type": "Number",
            "menu": "endOffset : Number readonly"
          },
          "startContainer": {
            "kind": "v",
            "type": "Node",
            "menu": "startContainer : Node readonly"
          },
          "startOffset": {
            "kind": "v",
            "type": "Number",
            "menu": "startOffset : Number readonly"
          },
          "cloneRange": {
            "kind": "f",
            "type": "Range",
            "menu": "cloneRange() : Range"
          },
          "compareBoundaryPoints": {
            "kind": "f",
            "type": "Number",
            "menu": "compareBoundaryPoints(how : Number, sourceRange : Range) : Number"
          },
          "deleteContents": {
            "kind": "f",
            "type": "undefined",
            "menu": "deleteContents() : undefined"
          },
          "detach": {
            "kind": "f",
            "type": "undefined",
            "menu": "detach() : undefined"
          },
          "extractContents": {
            "kind": "f",
            "type": "DocumentFragment",
            "menu": "extractContents() : DocumentFragment"
          },
          "insertNode": {
            "kind": "f",
            "type": "undefined",
            "menu": "insertNode(newNode : Node) : undefined"
          },
          "selectNode": {
            "kind": "f",
            "type": "undefined",
            "menu": "selectNode(refNode : Node) : undefined"
          },
          "selectNodeContents": {
            "kind": "f",
            "type": "undefined",
            "menu": "selectNodeContents(refNode : Node) : undefined"
          },
          "setEnd": {
            "kind": "f",
            "type": "undefined",
            "menu": "setEnd(refNode : Node, offset : Number) : undefined"
          },
          "setEndAfter": {
            "kind": "f",
            "type": "undefined",
            "menu": "setEndAfter(refNode : Node) : undefined"
          },
          "setEndBefore": {
            "kind": "f",
            "type": "undefined",
            "menu": "setEndBefore(refNode : Node) : undefined"
          },
          "setStart": {
            "kind": "f",
            "type": "undefined",
            "menu": "setStart(refNode : Node, offset : Number) : undefined"
          },
          "setStartAfter": {
            "kind": "f",
            "type": "undefined",
            "menu": "setStartAfter(refNode : Node) : undefined"
          },
          "setStartBefore": {
            "kind": "f",
            "type": "undefined",
            "menu": "setStartBefore(refNode : Node) : undefined"
          },
          "surroundContents": {
            "kind": "f",
            "type": "undefined",
            "menu": "surroundContents(newParent : Node) : undefined"
          },
          "cloneContents": {
            "kind": "f",
            "type": "DocumentFragment",
            "menu": "cloneContents() : DocumentFragment"
          }
        },
        "class": "Range",
        "type": "Object",
        "kind": "v"
      }
    }
  },
  "HTMLHeadElement": {
    "kind": "v"
  },
  "HTMLTitleElement": {
    "kind": "f",
    "props": {
      "prototype": {
        "props": {
          "text": {
            "kind": "v",
            "type": "String",
            "menu": "text : String"
          }
        },
        "class": "HTMLTitleElement",
        "type": "Object",
        "kind": "v"
      }
    }
  },
  "HTMLModElement": {
    "kind": "f",
    "props": {
      "prototype": {
        "props": {
          "dateTime": {
            "kind": "v",
            "type": "String",
            "menu": "dateTime : String"
          },
          "cite": {
            "kind": "v",
            "type": "String",
            "menu": "cite : String"
          }
        },
        "class": "HTMLModElement",
        "type": "Object",
        "kind": "v"
      }
    }
  },
  "CompositionEvent": {
    "kind": "f",
    "props": {
      "prototype": {
        "props": {
          "locale": {
            "kind": "v",
            "type": "String",
            "menu": "locale : String readonly"
          },
          "data": {
            "kind": "v",
            "type": "String",
            "menu": "data : String readonly"
          }
        },
        "class": "CompositionEvent",
        "type": "Object",
        "kind": "v"
      }
    }
  },
  "Document": {
    "kind": "f",
    "props": {
      "prototype": {
        "props": {
          "prepend": {
            "kind": "f",
            "type": "undefined",
            "menu": "prepend(node0 : Node, [node1 : Node, [...]]) : undefined"
          },
          "readyState": {
            "kind": "v",
            "type": "String",
            "menu": "readyState : String"
          },
          "styleSheets": {
            "kind": "v",
            "type": "StyleSheetList",
            "menu": "styleSheets : StyleSheetList"
          },
          "adoptNode": {
            "kind": "f",
            "type": "Node",
            "menu": "adoptNode(source : Node) : Node"
          },
          "append": {
            "kind": "f",
            "type": "undefined",
            "menu": "append(node0 : Node, [node1 : Node, [...]]) : undefined"
          },
          "createComment": {
            "kind": "f",
            "type": "Comment",
            "menu": "createComment(data : String) : Comment"
          },
          "createDocumentFragment": {
            "kind": "f",
            "type": "DocumentFragment",
            "menu": "createDocumentFragment() : DocumentFragment"
          },
          "querySelectorAll": {
            "kind": "f",
            "type": "NodeList",
            "menu": "querySelectorAll(cssSelector : String) : NodeList"
          },
          "documentURI": {
            "kind": "v",
            "type": "String",
            "menu": "documentURI : String"
          },
          "querySelector": {
            "kind": "f",
            "type": "Element",
            "menu": "querySelector(selectors : String) : Element"
          },
          "doctype": {
            "kind": "v",
            "type": "DocumentType",
            "menu": "doctype : DocumentType readonly"
          },
          "contentType": {
            "kind": "v",
            "type": "String",
            "menu": "contentType : String"
          },
          "compatMode": {
            "kind": "v",
            "type": "String",
            "menu": "compatMode : String"
          },
          "characterSet": {
            "kind": "v",
            "type": "String",
            "menu": "characterSet : String"
          },
          "body": {
            "kind": "v",
            "type": "HTMLBodyElement",
            "menu": "body : HTMLBodyElement"
          },
          "activeElement": {
            "kind": "v",
            "type": "Element",
            "menu": "activeElement : Element"
          },
          "URL": {
            "kind": "v",
            "type": "String",
            "menu": "URL : String"
          },
          "implementation": {
            "kind": "v",
            "type": "DOMImplementation",
            "menu": "implementation : DOMImplementation readonly"
          },
          "documentElement": {
            "kind": "v",
            "type": "Element",
            "menu": "documentElement : Element readonly"
          },
          "createElement": {
            "kind": "f",
            "type": "Element",
            "menu": "createElement(tagName : String) : Element"
          },
          "createElementNS": {
            "kind": "f",
            "type": "Element",
            "menu": "createElementNS(namespaceURI : String, qualifiedName : String) : Element"
          },
          "createEvent": {
            "kind": "f",
            "type": "Event",
            "menu": "createEvent(eventInterfaceName : String) : Event"
          },
          "createNodeIterator": {
            "kind": "f",
            "type": "NodeIterator",
            "menu": "createNodeIterator(root : Node, [whatToShow : Number, [filter : NodeFilter]]) : NodeIterator"
          },
          "createProcessingInstruction": {
            "kind": "f",
            "type": "ProcessingInstruction",
            "menu": "createProcessingInstruction(target : String, data : String) : ProcessingInstruction"
          },
          "createRange": {
            "kind": "f",
            "type": "Range",
            "menu": "createRange() : Range"
          },
          "createTextNode": {
            "kind": "f",
            "type": "Text",
            "menu": "createTextNode(data : String) : Text"
          },
          "createTreeWalker": {
            "kind": "f",
            "type": "TreeWalker",
            "menu": "createTreeWalker(root : Node, [whatToShow : Number, [filter : NodeFilter]]) : TreeWalker"
          },
          "getElementById": {
            "kind": "f",
            "type": "Element",
            "menu": "getElementById(elementId : String) : Element"
          },
          "getElementsByClassName": {
            "kind": "f",
            "type": "NodeList",
            "menu": "getElementsByClassName(classNames : String) : NodeList"
          },
          "getElementsByTagName": {
            "kind": "f",
            "type": "NodeList",
            "menu": "getElementsByTagName(tagname : String) : NodeList"
          },
          "getElementsByTagNameNS": {
            "kind": "f",
            "type": "NodeList",
            "menu": "getElementsByTagNameNS(namespaceURI : String, localName : String) : NodeList"
          },
          "hasFocus": {
            "kind": "f",
            "type": "Boolean",
            "menu": "hasFocus() : Boolean"
          },
          "importNode": {
            "kind": "f",
            "type": "Node",
            "menu": "importNode(importedNode : Node, deep : Boolean) : Node"
          }
        },
        "class": "Document",
        "type": "Object",
        "kind": "v"
      }
    }
  },
  "Storage": {
    "kind": "f",
    "props": {
      "prototype": {
        "props": {
          "setItem": {
            "kind": "f",
            "type": "undefined",
            "menu": "setItem(key : String, value : String) : undefined"
          },
          "removeItem": {
            "kind": "f",
            "type": "undefined",
            "menu": "removeItem(key : String) : undefined"
          },
          "key": {
            "kind": "f",
            "type": "String",
            "menu": "key(index : Number) : String"
          },
          "getItem": {
            "kind": "f",
            "type": "String",
            "menu": "getItem(key : String) : String"
          },
          "clear": {
            "kind": "f",
            "type": "undefined",
            "menu": "clear() : undefined"
          },
          "length": {
            "kind": "v",
            "type": "Number",
            "menu": "length : Number readonly"
          }
        },
        "class": "Storage",
        "type": "Object",
        "kind": "v"
      }
    }
  },
  "UIEvent": {
    "props": {
      "detail": {
        "kind": "v",
        "type": "Number",
        "menu": "detail : Number readonly"
      },
      "prototype": {
        "props": {
          "initUIEvent": {
            "kind": "f",
            "type": "undefined",
            "menu": "initUIEvent(type : String, bubbles : Boolean, cancelable : Boolean, view : Window, detail : Number) : undefined"
          },
          "view": {
            "kind": "v",
            "type": "Window",
            "menu": "view : Window readonly"
          }
        },
        "class": "UIEvent",
        "type": "Object",
        "kind": "v"
      }
    },
    "type": "UIEvent",
    "menu": "new UIEvent(type : String, [eventInit : Object]) : UIEvent",
    "kind": "f"
  },
  "HTMLParagraphElement": {
    "kind": "v"
  },
  "MutationObserver": {
    "props": {
      "prototype": {
        "props": {
          "takeRecords": {
            "kind": "f",
            "type": "Array",
            "menu": "takeRecords() : Array"
          },
          "observe": {
            "kind": "f",
            "type": "undefined",
            "menu": "observe(target : Node, options : Object) : undefined"
          },
          "disconnect": {
            "kind": "f",
            "type": "undefined",
            "menu": "disconnect() : undefined"
          }
        },
        "class": "MutationObserver",
        "type": "Object",
        "kind": "v"
      }
    },
    "type": "MutationObserver",
    "menu": "new MutationObserver(callback : Function) : MutationObserver",
    "kind": "f"
  },
  "HTMLHRElement": {
    "kind": "v"
  },
  "DOMSettableTokenList": {
    "kind": "f",
    "props": {
      "prototype": {
        "props": {
          "value": {
            "kind": "v",
            "type": "String",
            "menu": "value : String"
          }
        },
        "class": "DOMSettableTokenList",
        "type": "Object",
        "kind": "v"
      }
    }
  },
  "DOMParser": {
    "props": {
      "prototype": {
        "props": {
          "parseFromString": {
            "kind": "f",
            "type": "Document",
            "menu": "parseFromString(string : String, mimeType : String) : Document"
          }
        },
        "class": "DOMParser",
        "type": "Object",
        "kind": "v"
      }
    },
    "type": "DOMParser",
    "menu": "new DOMParser() : DOMParser",
    "kind": "f"
  },
  "HTMLOptGroupElement": {
    "kind": "f",
    "props": {
      "prototype": {
        "props": {
          "label": {
            "kind": "v",
            "type": "String",
            "menu": "label : String"
          },
          "disabled": {
            "kind": "v",
            "type": "Boolean",
            "menu": "disabled : Boolean"
          }
        },
        "class": "HTMLOptGroupElement",
        "type": "Object",
        "kind": "v"
      }
    }
  },
  "HTMLHeadingElement": {
    "kind": "v"
  },
  "ValidityState": {
    "kind": "f",
    "props": {
      "prototype": {
        "props": {
          "typeMismatch": {
            "kind": "v",
            "type": "Boolean",
            "menu": "typeMismatch : Boolean readonly"
          },
          "valid": {
            "kind": "v",
            "type": "Boolean",
            "menu": "valid : Boolean readonly"
          },
          "valueMissing": {
            "kind": "v",
            "type": "Boolean",
            "menu": "valueMissing : Boolean readonly"
          },
          "customError": {
            "kind": "v",
            "type": "Boolean",
            "menu": "customError : Boolean readonly"
          },
          "patternMismatch": {
            "kind": "v",
            "type": "Boolean",
            "menu": "patternMismatch : Boolean readonly"
          },
          "rangeOverflow": {
            "kind": "v",
            "type": "Boolean",
            "menu": "rangeOverflow : Boolean readonly"
          },
          "rangeUnderflow": {
            "kind": "v",
            "type": "Boolean",
            "menu": "rangeUnderflow : Boolean readonly"
          },
          "stepMismatch": {
            "kind": "v",
            "type": "Boolean",
            "menu": "stepMismatch : Boolean readonly"
          },
          "tooLong": {
            "kind": "v",
            "type": "Boolean",
            "menu": "tooLong : Boolean readonly"
          }
        },
        "class": "ValidityState",
        "type": "Object",
        "kind": "v"
      }
    }
  },
  "KeyboardEvent": {
    "kind": "f",
    "props": {
      "prototype": {
        "props": {
          "which": {
            "kind": "v",
            "type": "Number",
            "menu": "which : Number readonly"
          },
          "shiftKey": {
            "kind": "v",
            "type": "Boolean",
            "menu": "shiftKey : Boolean readonly"
          },
          "metaKey": {
            "kind": "v",
            "type": "Boolean",
            "menu": "metaKey : Boolean readonly"
          },
          "keyCode": {
            "kind": "v",
            "type": "Number",
            "menu": "keyCode : Number readonly"
          },
          "ctrlKey": {
            "kind": "v",
            "type": "Boolean",
            "menu": "ctrlKey : Boolean readonly"
          },
          "charCode": {
            "kind": "v",
            "type": "Number",
            "menu": "charCode : Number readonly"
          },
          "altKey": {
            "kind": "v",
            "type": "Boolean",
            "menu": "altKey : Boolean readonly"
          }
        },
        "class": "KeyboardEvent",
        "type": "Object",
        "kind": "v"
      }
    }
  },
  "HTMLInputElement": {
    "kind": "f",
    "props": {
      "prototype": {
        "props": {
          "defaultValue": {
            "kind": "v",
            "type": "String",
            "menu": "defaultValue : String"
          },
          "defaultChecked": {
            "kind": "v",
            "type": "Boolean",
            "menu": "defaultChecked : Boolean"
          },
          "checked": {
            "kind": "v",
            "type": "Boolean",
            "menu": "checked : Boolean"
          },
          "autofocus": {
            "kind": "v",
            "type": "Boolean",
            "menu": "autofocus : Boolean"
          },
          "autocomplete": {
            "kind": "v",
            "type": "String",
            "menu": "autocomplete : String"
          },
          "alt": {
            "kind": "v",
            "type": "String",
            "menu": "alt : String"
          },
          "accept": {
            "kind": "v",
            "type": "String",
            "menu": "accept : String"
          },
          "disabled": {
            "kind": "v",
            "type": "Boolean",
            "menu": "disabled : Boolean"
          },
          "files": {
            "kind": "v",
            "type": "FileList",
            "menu": "files : FileList readonly"
          },
          "form": {
            "kind": "v",
            "type": "HTMLFormElement",
            "menu": "form : HTMLFormElement readonly"
          },
          "formAction": {
            "kind": "v",
            "type": "String",
            "menu": "formAction : String"
          },
          "formEnctype": {
            "kind": "v",
            "type": "String",
            "menu": "formEnctype : String"
          },
          "formMethod": {
            "kind": "v",
            "type": "String",
            "menu": "formMethod : String"
          },
          "formNoValidate": {
            "kind": "v",
            "type": "Boolean",
            "menu": "formNoValidate : Boolean"
          },
          "formTarget": {
            "kind": "v",
            "type": "String",
            "menu": "formTarget : String"
          },
          "size": {
            "kind": "v",
            "type": "Number",
            "menu": "size : Number"
          },
          "width": {
            "kind": "v",
            "type": "Number",
            "menu": "width : Number"
          },
          "height": {
            "kind": "v",
            "type": "Number",
            "menu": "height : Number"
          },
          "indeterminate": {
            "kind": "v",
            "type": "Boolean",
            "menu": "indeterminate : Boolean"
          },
          "labels": {
            "kind": "v",
            "type": "NodeList",
            "menu": "labels : NodeList readonly"
          },
          "list": {
            "kind": "v",
            "type": "HTMLElement",
            "menu": "list : HTMLElement readonly"
          },
          "max": {
            "kind": "v",
            "type": "String",
            "menu": "max : String"
          },
          "maxLength": {
            "kind": "v",
            "type": "Number",
            "menu": "maxLength : Number"
          },
          "min": {
            "kind": "v",
            "type": "String",
            "menu": "min : String"
          },
          "multiple": {
            "kind": "v",
            "type": "Boolean",
            "menu": "multiple : Boolean"
          },
          "selectionStart": {
            "kind": "v",
            "type": "Number",
            "menu": "selectionStart : Number"
          },
          "selectionEnd": {
            "kind": "v",
            "type": "Number",
            "menu": "selectionEnd : Number"
          },
          "selectionDirection": {
            "kind": "v",
            "type": "String",
            "menu": "selectionDirection : String"
          },
          "required": {
            "kind": "v",
            "type": "Boolean",
            "menu": "required : Boolean"
          },
          "readOnly": {
            "kind": "v",
            "type": "Boolean",
            "menu": "readOnly : Boolean"
          },
          "placeholder": {
            "kind": "v",
            "type": "String",
            "menu": "placeholder : String"
          },
          "pattern": {
            "kind": "v",
            "type": "String",
            "menu": "pattern : String"
          },
          "name": {
            "kind": "v",
            "type": "String",
            "menu": "name : String"
          },
          "dirName": {
            "kind": "v",
            "type": "String",
            "menu": "dirName : String"
          },
          "src": {
            "kind": "v",
            "type": "String",
            "menu": "src : String"
          },
          "step": {
            "kind": "v",
            "type": "String",
            "menu": "step : String"
          },
          "type": {
            "kind": "v",
            "type": "String",
            "menu": "type : String"
          },
          "validationMessage": {
            "kind": "v",
            "type": "String",
            "menu": "validationMessage : String readonly"
          },
          "validity": {
            "kind": "v",
            "type": "ValidityState",
            "menu": "validity : ValidityState readonly"
          },
          "value": {
            "kind": "v",
            "type": "String",
            "menu": "value : String"
          },
          "valueAsDate": {
            "kind": "v",
            "type": "Date",
            "menu": "valueAsDate : Date"
          },
          "valueAsNumber": {
            "kind": "v",
            "type": "Number",
            "menu": "valueAsNumber : Number"
          },
          "stepUp": {
            "kind": "f",
            "type": "undefined",
            "menu": "stepUp([n : Number]) : undefined"
          },
          "stepDown": {
            "kind": "f",
            "type": "undefined",
            "menu": "stepDown([n : Number]) : undefined"
          },
          "setSelectionRange": {
            "kind": "f",
            "type": "undefined",
            "menu": "setSelectionRange(start : Number, end : Number, [direction : String]) : undefined"
          },
          "setCustomValidity": {
            "kind": "f",
            "type": "undefined",
            "menu": "setCustomValidity(error : String) : undefined"
          },
          "select": {
            "kind": "f",
            "type": "undefined",
            "menu": "select() : undefined"
          },
          "checkValidity": {
            "kind": "f",
            "type": "Boolean",
            "menu": "checkValidity() : Boolean"
          },
          "willValidate": {
            "kind": "v",
            "type": "Boolean",
            "menu": "willValidate : Boolean readonly"
          }
        },
        "class": "HTMLInputElement",
        "type": "Object",
        "kind": "v"
      }
    }
  },
  "HTMLMetaElement": {
    "kind": "f",
    "props": {
      "prototype": {
        "props": {
          "name": {
            "kind": "v",
            "type": "String",
            "menu": "name : String"
          },
          "httpEquiv": {
            "kind": "v",
            "type": "String",
            "menu": "httpEquiv : String"
          },
          "content": {
            "kind": "v",
            "type": "String",
            "menu": "content : String"
          }
        },
        "class": "HTMLMetaElement",
        "type": "Object",
        "kind": "v"
      }
    }
  },
  "HTMLBRElement": {
    "kind": "v"
  },
  "Event": {
    "props": {
      "NONE": {
        "kind": "v",
        "type": "Number",
        "menu": "NONE : Number readonly"
      },
      "CAPTURING_PHASE": {
        "kind": "v",
        "type": "Number",
        "menu": "CAPTURING_PHASE : Number readonly"
      },
      "BUBBLING_PHASE": {
        "kind": "v",
        "type": "Number",
        "menu": "BUBBLING_PHASE : Number readonly"
      },
      "AT_TARGET": {
        "kind": "v",
        "type": "Number",
        "menu": "AT_TARGET : Number readonly"
      },
      "prototype": {
        "props": {
          "currentTarget": {
            "kind": "v",
            "type": "Object",
            "menu": "currentTarget : Object readonly"
          },
          "cancelable": {
            "kind": "v",
            "type": "Boolean",
            "menu": "cancelable : Boolean readonly"
          },
          "bubbles": {
            "kind": "v",
            "type": "Boolean",
            "menu": "bubbles : Boolean readonly"
          },
          "type": {
            "kind": "v",
            "type": "String",
            "menu": "type : String readonly"
          },
          "initEvent": {
            "kind": "f",
            "type": "undefined",
            "menu": "initEvent(type : String, canBubble : Boolean, cancelable : Boolean) : undefined"
          },
          "timeStamp": {
            "kind": "v",
            "type": "Number",
            "menu": "timeStamp : Number readonly"
          },
          "target": {
            "kind": "v",
            "type": "Object",
            "menu": "target : Object readonly"
          },
          "isTrusted": {
            "kind": "v",
            "type": "Boolean",
            "menu": "isTrusted : Boolean readonly"
          },
          "eventPhase": {
            "kind": "v",
            "type": "Number",
            "menu": "eventPhase : Number readonly"
          },
          "defaultPrevented": {
            "kind": "v",
            "type": "Boolean",
            "menu": "defaultPrevented : Boolean readonly"
          },
          "stopPropagation": {
            "kind": "f",
            "type": "undefined",
            "menu": "stopPropagation() : undefined"
          },
          "stopImmediatePropagation": {
            "kind": "f",
            "type": "undefined",
            "menu": "stopImmediatePropagation() : undefined"
          },
          "preventDefault": {
            "kind": "f",
            "type": "undefined",
            "menu": "preventDefault() : undefined"
          }
        },
        "class": "Event",
        "type": "Object",
        "kind": "v"
      }
    },
    "type": "Event",
    "menu": "new Event(type : String, [eventInit : Object]) : Event",
    "kind": "f"
  },
  "NodeIterator": {
    "kind": "v"
  },
  "DOMTokenList": {
    "kind": "f",
    "props": {
      "prototype": {
        "props": {
          "toggle": {
            "kind": "f",
            "type": "Boolean",
            "menu": "toggle(token : String) : Boolean"
          },
          "remove": {
            "kind": "f",
            "type": "undefined",
            "menu": "remove(token : String) : undefined"
          },
          "item": {
            "kind": "f",
            "type": "String",
            "menu": "item(index : Number) : String"
          },
          "contains": {
            "kind": "f",
            "type": "Boolean",
            "menu": "contains(token : String) : Boolean"
          },
          "add": {
            "kind": "f",
            "type": "undefined",
            "menu": "add(token : String) : undefined"
          },
          "length": {
            "kind": "v",
            "type": "Number",
            "menu": "length : Number readonly"
          }
        },
        "class": "DOMTokenList",
        "type": "Object",
        "kind": "v"
      }
    }
  },
  "HTMLCanvasElement": {
    "kind": "f",
    "props": {
      "prototype": {
        "props": {
          "toDataURL": {
            "kind": "f",
            "type": "String",
            "menu": "toDataURL([type = 'image/png' : String, [jpegCompressionRatio : Number]]) : String"
          },
          "getContext": {
            "kind": "f",
            "type": "CanvasRenderingContext",
            "menu": "getContext(contextType : String, [contextAttributes : Object]) : CanvasRenderingContext"
          },
          "width": {
            "kind": "v",
            "type": "Number",
            "menu": "width : Number"
          },
          "height": {
            "kind": "v",
            "type": "Number",
            "menu": "height : Number"
          }
        },
        "class": "HTMLCanvasElement",
        "type": "Object",
        "kind": "v"
      }
    }
  },
  "HTMLOptionsCollection": {
    "kind": "f",
    "props": {
      "prototype": {
        "props": {
          "remove": {
            "kind": "f",
            "type": "undefined",
            "menu": "remove(index : Number) : undefined"
          },
          "selectedIndex": {
            "kind": "v",
            "type": "Number",
            "menu": "selectedIndex : Number"
          },
          "length": {
            "kind": "v",
            "type": "Number",
            "menu": "length : Number"
          }
        },
        "class": "HTMLOptionsCollection",
        "type": "Object",
        "kind": "v"
      }
    }
  },
  "Element": {
    "kind": "f",
    "props": {
      "prototype": {
        "props": {
          "dispatchEvent": {
            "kind": "f",
            "type": "Boolean",
            "menu": "dispatchEvent(event : Event) : Boolean"
          },
          "addEventListener": {
            "kind": "f",
            "type": "undefined",
            "menu": "addEventListener(eventType : String, listener : (EventListener|Function) [, useCapture : Boolean]) : undefined"
          },
          "removeEventListener": {
            "kind": "f",
            "type": "undefined",
            "menu": "removeEventListener(eventType : String, listener : (EventListener|Function) [, useCapture : Boolean]) : undefined"
          },
          "getAttribute": {
            "kind": "f",
            "type": "String",
            "menu": "getAttribute(name : String) : String"
          },
          "tagName": {
            "kind": "v",
            "type": "String",
            "menu": "tagName : String readonly"
          },
          "scrollWidth": {
            "kind": "v",
            "type": "Number",
            "menu": "scrollWidth : Number readonly"
          },
          "scrollTop": {
            "kind": "v",
            "type": "Number",
            "menu": "scrollTop : Number"
          },
          "scrollLeft": {
            "kind": "v",
            "type": "Number",
            "menu": "scrollLeft : Number"
          },
          "scrollHeight": {
            "kind": "v",
            "type": "Number",
            "menu": "scrollHeight : Number readonly"
          },
          "previousElementSibling": {
            "kind": "v",
            "type": "Element",
            "menu": "previousElementSibling : Element"
          },
          "prefix": {
            "kind": "v",
            "type": "String",
            "menu": "prefix : String"
          },
          "nextElementSibling": {
            "kind": "v",
            "type": "Element",
            "menu": "nextElementSibling : Element"
          },
          "namespaceURI": {
            "kind": "v",
            "type": "String",
            "menu": "namespaceURI : String"
          },
          "localName": {
            "kind": "v",
            "type": "String",
            "menu": "localName : String"
          },
          "lastElementChild": {
            "kind": "v",
            "type": "Element",
            "menu": "lastElementChild : Element"
          },
          "id": {
            "kind": "v",
            "type": "String",
            "menu": "id : String"
          },
          "firstElementChild": {
            "kind": "v",
            "type": "Element",
            "menu": "firstElementChild : Element"
          },
          "dataset": {
            "kind": "v",
            "type": "DOMStringMap",
            "menu": "dataset : DOMStringMap"
          },
          "offsetTop": {
            "kind": "v",
            "type": "Number",
            "menu": "offsetTop : Number readonly"
          },
          "offsetLeft": {
            "kind": "v",
            "type": "Number",
            "menu": "offsetLeft : Number readonly"
          },
          "offsetWidth": {
            "kind": "v",
            "type": "Number",
            "menu": "offsetWidth : Number readonly"
          },
          "offsetHeight": {
            "kind": "v",
            "type": "Number",
            "menu": "offsetWidth : Number readonly"
          },
          "clientWidth": {
            "kind": "v",
            "type": "Number",
            "menu": "clientWidth : Number readonly"
          },
          "hasAttributeNS": {
            "kind": "f",
            "type": "Boolean",
            "menu": "hasAttributeNS(namespaceURI : String, localName : String) : Boolean"
          },
          "hasAttribute": {
            "kind": "f",
            "type": "Boolean",
            "menu": "hasAttribute(name : String) : Boolean"
          },
          "getElementsByTagNameNS": {
            "kind": "f",
            "type": "NodeList",
            "menu": "getElementsByTagNameNS(namespaceURI : String, localName : String) : NodeList"
          },
          "getElementsByTagName": {
            "kind": "f",
            "type": "NodeList",
            "menu": "getElementsByTagName(name : String) : NodeList"
          },
          "getElementsByClassName": {
            "kind": "f",
            "type": "NodeList",
            "menu": "getElementsByClassName(classNames : String) : NodeList"
          },
          "getClientRects": {
            "kind": "f",
            "type": "ClientRectList",
            "menu": "getClientRects() : ClientRectList"
          },
          "getBoundingClientRect": {
            "kind": "f",
            "type": "ClientRect",
            "menu": "getBoundingClientRect() : ClientRect"
          },
          "getAttributeNS": {
            "kind": "f",
            "type": "String",
            "menu": "getAttributeNS(namespaceURI : String, localName : String) : String"
          },
          "setAttributeNS": {
            "kind": "f",
            "type": "undefined",
            "menu": "setAttributeNS(namespaceURI : String, qualifiedName : String, value : String) : undefined"
          },
          "setAttribute": {
            "kind": "f",
            "type": "undefined",
            "menu": "setAttribute(name : String, value : String) : undefined"
          },
          "scrollIntoView": {
            "kind": "f",
            "type": "undefined",
            "menu": "scrollIntoView([top = false : Boolean]) : undefined"
          },
          "removeAttributeNS": {
            "kind": "f",
            "type": "undefined",
            "menu": "removeAttributeNS(namespaceURI : String, localName : String) : undefined"
          },
          "removeAttribute": {
            "kind": "f",
            "type": "undefined",
            "menu": "removeAttribute(name : String) : undefined"
          },
          "querySelectorAll": {
            "kind": "f",
            "type": "NodeList",
            "menu": "querySelectorAll(cssSelector : String) : NodeList"
          },
          "querySelector": {
            "kind": "f",
            "type": "Element",
            "menu": "querySelector(selectors : String) : Element"
          },
          "hasAttributes": {
            "kind": "f",
            "type": "Boolean",
            "menu": "hasAttributes() : Boolean"
          },
          "Attributes": {
            "kind": "v",
            "type": "Array",
            "menu": "Attributes : Array"
          },
          "childElementCount": {
            "kind": "v",
            "type": "Number",
            "menu": "childElementCount : Number"
          },
          "children": {
            "kind": "v",
            "type": "HTMLCollection",
            "menu": "children : HTMLCollection"
          },
          "classList": {
            "kind": "v",
            "type": "DOMTokenList",
            "menu": "classList : DOMTokenList"
          },
          "className": {
            "kind": "v",
            "type": "String",
            "menu": "className : String"
          },
          "clientHeight": {
            "kind": "v",
            "type": "Number",
            "menu": "clientHeight : Number readonly"
          },
          "clientLeft": {
            "kind": "v",
            "type": "Number",
            "menu": "clientLeft : Number readonly"
          },
          "clientTop": {
            "kind": "v",
            "type": "Number",
            "menu": "clientTop : Number readonly"
          }
        },
        "class": "Element",
        "type": "Object",
        "kind": "v"
      }
    }
  },
  "HTMLStyleElement": {
    "kind": "f",
    "props": {
      "prototype": {
        "props": {
          "type": {
            "kind": "v",
            "type": "String",
            "menu": "type : String"
          },
          "scoped": {
            "kind": "v",
            "type": "Boolean",
            "menu": "scoped : Boolean"
          },
          "media": {
            "kind": "v",
            "type": "String",
            "menu": "media : String"
          },
          "disabled": {
            "kind": "v",
            "type": "Boolean",
            "menu": "disabled : Boolean"
          }
        },
        "class": "HTMLStyleElement",
        "type": "Object",
        "kind": "v"
      }
    }
  },
  "Node": {
    "kind": "f",
    "props": {
      "DOCUMENT_TYPE_NODE": {
        "kind": "v",
        "type": "Number",
        "menu": "DOCUMENT_TYPE_NODE : Number readonly"
      },
      "DOCUMENT_POSITION_PRECEDING": {
        "kind": "v",
        "type": "Number",
        "menu": "DOCUMENT_POSITION_PRECEDING : Number readonly"
      },
      "DOCUMENT_POSITION_IMPLEMENTATION_SPECIFIC": {
        "kind": "v",
        "type": "Number",
        "menu": "DOCUMENT_POSITION_IMPLEMENTATION_SPECIFIC : Number readonly"
      },
      "DOCUMENT_POSITION_CONTAINS": {
        "kind": "v",
        "type": "Number",
        "menu": "DOCUMENT_POSITION_CONTAINS : Number readonly"
      },
      "DOCUMENT_POSITION_CONTAINED_BY": {
        "kind": "v",
        "type": "Number",
        "menu": "DOCUMENT_POSITION_CONTAINED_BY : Number readonly"
      },
      "DOCUMENT_NODE": {
        "kind": "v",
        "type": "Number",
        "menu": "DOCUMENT_NODE : Number readonly"
      },
      "DOCUMENT_FRAGMENT_NODE": {
        "kind": "v",
        "type": "Number",
        "menu": "DOCUMENT_FRAGMENT_NODE : Number readonly"
      },
      "COMMENT_NODE": {
        "kind": "v",
        "type": "Number",
        "menu": "COMMENT_NODE : Number readonly"
      },
      "ELEMENT_NODE": {
        "kind": "v",
        "type": "Number",
        "menu": "ELEMENT_NODE : Number readonly"
      },
      "ENTITY_NODE": {
        "kind": "v",
        "type": "Number",
        "menu": "ENTITY_NODE : Number readonly"
      },
      "ENTITY_REFERENCE_NODE": {
        "kind": "v",
        "type": "Number",
        "menu": "ENTITY_REFERENCE_NODE : Number readonly"
      },
      "NOTATION_NODE": {
        "kind": "v",
        "type": "Number",
        "menu": "NOTATION_NODE : Number readonly"
      },
      "PROCESSING_INSTRUCTION_NODE": {
        "kind": "v",
        "type": "Number",
        "menu": "PROCESSING_INSTRUCTION_NODE : Number readonly"
      },
      "TEXT_NODE": {
        "kind": "v",
        "type": "Number",
        "menu": "TEXT_NODE : Number readonly"
      },
      "CDATA_SECTION_NODE": {
        "kind": "v",
        "type": "Number",
        "menu": "CDATA_SECTION_NODE : Number readonly"
      },
      "ATTRIBUTE_NODE": {
        "kind": "v",
        "type": "Number",
        "menu": "ATTRIBUTE_NODE : Number readonly"
      },
      "prototype": {
        "props": {
          "firstChild": {
            "kind": "v",
            "type": "Node",
            "menu": "firstChild : Node readonly"
          },
          "lastChild": {
            "kind": "v",
            "type": "Node",
            "menu": "lastChild : Node readonly"
          },
          "nextSibling": {
            "kind": "v",
            "type": "Node",
            "menu": "nextSibling : Node readonly"
          },
          "nodeName": {
            "kind": "v",
            "type": "String",
            "menu": "nodeName : String readonly"
          },
          "nodeType": {
            "kind": "v",
            "type": "Number",
            "menu": "nodeType : Number readonly"
          },
          "nodeValue": {
            "kind": "v",
            "type": "String",
            "menu": "nodeValue : String"
          },
          "contains": {
            "kind": "f",
            "type": "Boolean",
            "menu": "contains(other : Node) : Boolean"
          },
          "hasChildNodes": {
            "kind": "f",
            "type": "Boolean",
            "menu": "hasChildNodes() : Boolean"
          },
          "replaceChild": {
            "kind": "f",
            "type": "Node",
            "menu": "replaceChild(newChild : Node, oldChild : Node) : Node"
          },
          "removeChild": {
            "kind": "f",
            "type": "Node",
            "menu": "removeChild(oldChild : Node) : Node"
          },
          "ownerDocument": {
            "kind": "v",
            "type": "Document",
            "menu": "ownerDocument : Document readonly"
          },
          "parentElement": {
            "kind": "v",
            "type": "Element",
            "menu": "parentElement : Element readonly"
          },
          "parentNode": {
            "kind": "v",
            "type": "Node",
            "menu": "parentNode : Node readonly"
          },
          "previousSibling": {
            "kind": "v",
            "type": "Node",
            "menu": "previousSibling : Node readonly"
          },
          "textContent": {
            "kind": "v",
            "type": "String",
            "menu": "textContent : String"
          },
          "appendChild": {
            "kind": "f",
            "type": "Node",
            "menu": "appendChild(newChild : Node) : Node"
          },
          "cloneNode": {
            "kind": "f",
            "type": "Node",
            "menu": "cloneNode(deep : Boolean) : Node"
          },
          "compareDocumentPosition": {
            "kind": "f",
            "type": "Number",
            "menu": "compareDocumentPosition(other : Node) : Number"
          },
          "baseURI": {
            "kind": "v",
            "type": "String",
            "menu": "baseURI : String readonly"
          },
          "childNodes": {
            "kind": "v",
            "type": "NodeList",
            "menu": "childNodes : NodeList readonly"
          },
          "insertBefore": {
            "kind": "f",
            "type": "Node",
            "menu": "insertBefore(newChild : Node, [refChild : Node]) : Node"
          },
          "isDefaultNamespace": {
            "kind": "f",
            "type": "Boolean",
            "menu": "isDefaultNamespace(namespaceURI : Boolean) : Boolean"
          },
          "isEqualNode": {
            "kind": "f",
            "type": "Boolean",
            "menu": "isEqualNode(arg : Node) : Boolean"
          },
          "lookupNamespaceURI": {
            "kind": "f",
            "type": "String",
            "menu": "lookupNamespaceURI(prefix : String) : String"
          },
          "lookupPrefix": {
            "kind": "f",
            "type": "String",
            "menu": "lookupPrefix(namespaceURI : String) : String"
          },
          "normalize": {
            "kind": "f",
            "type": "undefined",
            "menu": "normalize() : undefined"
          }
        },
        "class": "Node",
        "type": "Object",
        "kind": "v"
      },
      "DOCUMENT_POSITION_DISCONNECTED": {
        "kind": "v",
        "type": "Number",
        "menu": "DOCUMENT_POSITION_DISCONNECTED : Number readonly"
      },
      "DOCUMENT_POSITION_FOLLOWING": {
        "kind": "v",
        "type": "Number",
        "menu": "DOCUMENT_POSITION_FOLLOWING : Number readonly"
      }
    }
  },
  "HTMLOListElement": {
    "kind": "f",
    "props": {
      "prototype": {
        "props": {
          "type": {
            "kind": "v",
            "type": "String",
            "menu": "type : String"
          },
          "start": {
            "kind": "v",
            "type": "Number",
            "menu": "start : Number"
          },
          "reversed": {
            "kind": "v",
            "type": "Boolean",
            "menu": "reversed : Boolean"
          }
        },
        "class": "HTMLOListElement",
        "type": "Object",
        "kind": "v"
      }
    }
  },
  "EventTarget": {
    "kind": "f",
    "props": {
      "prototype": {
        "props": {
          "dispatchEvent": {
            "kind": "f",
            "type": "Boolean",
            "menu": "dispatchEvent(event : Event) : Boolean"
          }
        },
        "class": "EventTarget",
        "type": "Object",
        "kind": "v"
      }
    }
  },
  "EventListener": {
    "kind": "f",
    "props": {
      "prototype": {
        "props": {
          "handleEvent": {
            "kind": "f",
            "type": "undefined",
            "menu": "handleEvent(event : Event) : undefined"
          }
        },
        "class": "EventListener",
        "type": "Object",
        "kind": "v"
      }
    }
  },
  "HTMLDListElement": {
    "kind": "v"
  },
  "XMLDocument": {
    "kind": "v"
  },
  "TreeWalker": {
    "kind": "v"
  },
  "HTMLAnchorElement": {
    "kind": "f",
    "props": {
      "prototype": {
        "props": {
          "hash": {
            "kind": "v",
            "type": "String",
            "menu": "hash : String"
          },
          "protocol": {
            "kind": "v",
            "type": "String",
            "menu": "protocol : String"
          },
          "rel": {
            "kind": "v",
            "type": "String",
            "menu": "rel : String"
          },
          "relList": {
            "kind": "v",
            "type": "DOMTokenList",
            "menu": "relList : DOMTokenList readonly"
          },
          "search": {
            "kind": "v",
            "type": "String",
            "menu": "search : String"
          },
          "target": {
            "kind": "v",
            "type": "String",
            "menu": "target : String"
          },
          "text": {
            "kind": "v",
            "type": "String",
            "menu": "text : String"
          },
          "port": {
            "kind": "v",
            "type": "String",
            "menu": "port : String"
          },
          "pathname": {
            "kind": "v",
            "type": "String",
            "menu": "pathname : String"
          },
          "media": {
            "kind": "v",
            "type": "String",
            "menu": "media : String"
          },
          "hreflang": {
            "kind": "v",
            "type": "String",
            "menu": "hreflang : String"
          },
          "href": {
            "kind": "v",
            "type": "String",
            "menu": "href : String"
          },
          "hostname": {
            "kind": "v",
            "type": "String",
            "menu": "hostname : String"
          },
          "host": {
            "kind": "v",
            "type": "String",
            "menu": "host : String"
          },
          "type": {
            "kind": "v",
            "type": "String",
            "menu": "type : String"
          }
        },
        "class": "HTMLAnchorElement",
        "type": "Object",
        "kind": "v"
      }
    }
  },
  "HTMLSelectElement": {
    "kind": "f",
    "props": {
      "prototype": {
        "props": {
          "selectedOptions": {
            "kind": "v",
            "type": "HTMLCollection",
            "menu": "selectedOptions : HTMLCollection readonly"
          },
          "selectedIndex": {
            "kind": "v",
            "type": "Number",
            "menu": "selectedIndex : Number"
          },
          "required": {
            "kind": "v",
            "type": "Boolean",
            "menu": "required : Boolean"
          },
          "options": {
            "kind": "v",
            "type": "HTMLOptionsCollection",
            "menu": "options : HTMLOptionsCollection readonly"
          },
          "name": {
            "kind": "v",
            "type": "String",
            "menu": "name : String"
          },
          "multiple": {
            "kind": "v",
            "type": "Boolean",
            "menu": "multiple : Boolean"
          },
          "length": {
            "kind": "v",
            "type": "Number",
            "menu": "length : Number"
          },
          "labels": {
            "kind": "v",
            "type": "NodeList",
            "menu": "labels : NodeList readonly"
          },
          "size": {
            "kind": "v",
            "type": "Number",
            "menu": "size : Number"
          },
          "type": {
            "kind": "v",
            "type": "String",
            "menu": "type : String readonly"
          },
          "validationMessage": {
            "kind": "v",
            "type": "String",
            "menu": "validationMessage : String readonly"
          },
          "validity": {
            "kind": "v",
            "type": "ValidityState",
            "menu": "validity : ValidityState readonly"
          },
          "value": {
            "kind": "v",
            "type": "String",
            "menu": "value : String"
          },
          "willValidate": {
            "kind": "v",
            "type": "Boolean",
            "menu": "willValidate : Boolean readonly"
          },
          "remove": {
            "kind": "f",
            "type": "undefined",
            "menu": "remove(index : Number) : undefined"
          },
          "setCustomValidity": {
            "kind": "f",
            "type": "undefined",
            "menu": "setCustomValidity(error : String) : undefined"
          },
          "form": {
            "kind": "v",
            "type": "HTMLFormElement",
            "menu": "form : HTMLFormElement readonly"
          },
          "disabled": {
            "kind": "v",
            "type": "Boolean",
            "menu": "disabled : Boolean"
          },
          "checkValidity": {
            "kind": "v",
            "type": "Boolean",
            "menu": "checkValidity : Boolean"
          },
          "autofocus": {
            "kind": "v",
            "type": "Boolean",
            "menu": "autofocus : Boolean"
          }
        },
        "class": "HTMLSelectElement",
        "type": "Object",
        "kind": "v"
      }
    }
  },
  "HTMLCollection": {
    "kind": "f",
    "props": {
      "prototype": {
        "props": {
          "namedItem": {
            "kind": "f",
            "type": "Element",
            "menu": "namedItem(name : String) : Element"
          },
          "item": {
            "kind": "f",
            "type": "Element",
            "menu": "item(index : Number) : Element"
          },
          "length": {
            "kind": "v",
            "type": "Number",
            "menu": "length : Number readonly"
          }
        },
        "class": "HTMLCollection",
        "type": "Object",
        "kind": "v"
      }
    }
  },
  "HTMLFormElement": {
    "kind": "f",
    "props": {
      "prototype": {
        "props": {
          "action": {
            "kind": "v",
            "type": "String",
            "menu": "action : String"
          },
          "acceptCharset": {
            "kind": "v",
            "type": "String",
            "menu": "acceptCharset : String"
          },
          "name": {
            "kind": "v",
            "type": "String",
            "menu": "name : String"
          },
          "noValidate": {
            "kind": "v",
            "type": "Boolean",
            "menu": "noValidate : Boolean"
          },
          "target": {
            "kind": "v",
            "type": "String",
            "menu": "target : String"
          },
          "checkValidity": {
            "kind": "f",
            "type": "Boolean",
            "menu": "checkValidity() : Boolean"
          },
          "method": {
            "kind": "v",
            "type": "String",
            "menu": "method : String"
          },
          "length": {
            "kind": "v",
            "type": "Number",
            "menu": "length : Number readonly"
          },
          "enctype": {
            "kind": "v",
            "type": "String",
            "menu": "enctype : String"
          },
          "encoding": {
            "kind": "v",
            "type": "String",
            "menu": "encoding : String"
          },
          "elements": {
            "kind": "v",
            "type": "HTMLFormControlsCollection",
            "menu": "elements : HTMLFormControlsCollection readonly"
          },
          "autocomplete": {
            "kind": "v",
            "type": "String",
            "menu": "autocomplete : String"
          },
          "submit": {
            "kind": "f",
            "type": "undefined",
            "menu": "submit() : undefined"
          },
          "reset": {
            "kind": "f",
            "type": "undefined",
            "menu": "reset() : undefined"
          }
        },
        "class": "HTMLFormElement",
        "type": "Object",
        "kind": "v"
      }
    }
  },
  "HTMLOptionElement": {
    "kind": "f",
    "props": {
      "prototype": {
        "props": {
          "value": {
            "kind": "v",
            "type": "String",
            "menu": "value : String"
          },
          "text": {
            "kind": "v",
            "type": "String",
            "menu": "text : String"
          },
          "selected": {
            "kind": "v",
            "type": "Boolean",
            "menu": "selected : Boolean"
          },
          "label": {
            "kind": "v",
            "type": "String",
            "menu": "label : String"
          },
          "index": {
            "kind": "v",
            "type": "Number",
            "menu": "index : Number readonly"
          },
          "form": {
            "kind": "v",
            "type": "HTMLFormElement",
            "menu": "form : HTMLFormElement readonly"
          },
          "disabled": {
            "kind": "v",
            "type": "Boolean",
            "menu": "disabled : Boolean"
          },
          "defaultSelected": {
            "kind": "v",
            "type": "Boolean",
            "menu": "defaultSelected : Boolean"
          }
        },
        "class": "HTMLOptionElement",
        "type": "Object",
        "kind": "v"
      }
    }
  },
  "FocusEvent": {
    "props": {
      "detail": {
        "kind": "v",
        "type": "Number",
        "menu": "detail : Number readonly"
      },
      "prototype": {
        "props": {
          "initUIEvent": {
            "kind": "f",
            "type": "undefined",
            "menu": "initUIEvent(type : String, bubbles : Boolean, cancelable : Boolean, view : Window, detail : Number) : undefined"
          },
          "view": {
            "kind": "v",
            "type": "Window",
            "menu": "view : Window readonly"
          }
        },
        "class": "FocusEvent",
        "type": "Object",
        "kind": "v"
      }
    },
    "type": "Event",
    "menu": "new FocusEvent(type : String, [eventInit : Object]) : Event",
    "kind": "f"
  },
  "Text": {
    "kind": "v"
  },
  "HTMLSpanElement": {
    "kind": "v"
  },
  "ClientRectList": {
    "kind": "f",
    "props": {
      "prototype": {
        "props": {
          "item": {
            "kind": "f",
            "type": "ClientRect",
            "menu": "item(index : Number) : ClientRect"
          },
          "length": {
            "kind": "v",
            "type": "Number",
            "menu": "length : Number"
          }
        },
        "class": "ClientRectList",
        "type": "Object",
        "kind": "v"
      }
    }
  },
  "HTMLFormControlsCollection": {
    "kind": "v"
  },
  "NodeFilter": {
    "kind": "f",
    "props": {
      "SHOW_DOCUMENT_FRAGMENT": {
        "kind": "v",
        "type": "Number",
        "menu": "SHOW_DOCUMENT_FRAGMENT : Number readonly value = 1024"
      },
      "SHOW_DOCUMENT_TYPE": {
        "kind": "v",
        "type": "Number",
        "menu": "SHOW_DOCUMENT_TYPE : Number readonly value = 512"
      },
      "SHOW_ELEMENT": {
        "kind": "v",
        "type": "Number",
        "menu": "SHOW_ELEMENT : Number readonly value = 1"
      },
      "SHOW_ENTITY": {
        "kind": "v",
        "type": "Number",
        "menu": "SHOW_ENTITY : Number readonly value = 32"
      },
      "SHOW_ENTITY_REFERENCE": {
        "kind": "v",
        "type": "Number",
        "menu": "SHOW_ENTITY_REFERENCE : Number readonly value = 16"
      },
      "SHOW_NOTATION": {
        "kind": "v",
        "type": "Number",
        "menu": "SHOW_NOTATION : Number readonly value = 2048"
      },
      "SHOW_PROCESSING_INSTRUCTION": {
        "kind": "v",
        "type": "Number",
        "menu": "SHOW_PROCESSING_INSTRUCTION : Number readonly value = 64"
      },
      "SHOW_TEXT": {
        "kind": "v",
        "type": "Number",
        "menu": "SHOW_TEXT : Number readonly value = 4"
      },
      "SHOW_DOCUMENT": {
        "kind": "v",
        "type": "Number",
        "menu": "SHOW_DOCUMENT : Number readonly value = 256"
      },
      "SHOW_COMMENT": {
        "kind": "v",
        "type": "Number",
        "menu": "SHOW_COMMENT : Number readonly value = 128"
      },
      "SHOW_CDATA_SECTION": {
        "kind": "v",
        "type": "Number",
        "menu": "SHOW_CDATA_SECTION : Number readonly value = 8"
      },
      "SHOW_ATTRIBUTE": {
        "kind": "v",
        "type": "Number",
        "menu": "SHOW_ATTRIBUTE : Number readonly value = 2"
      },
      "SHOW_ALL": {
        "kind": "v",
        "type": "Number",
        "menu": "SHOW_ALL : Number readonly value = 4294967295"
      },
      "FILTER_REJECT": {
        "kind": "v",
        "type": "Number",
        "menu": "FILTER_REJECT : Number readonly value = 2"
      },
      "FILTER_ACCEPT": {
        "kind": "v",
        "type": "Number",
        "menu": "FILTER_ACCEPT : Number readonly value = 1"
      },
      "prototype": {
        "props": {
          "acceptNode": {
            "kind": "f",
            "type": "Number",
            "menu": "acceptNode(n : Node) : Number"
          }
        },
        "class": "NodeFilter",
        "type": "Object",
        "kind": "v"
      }
    }
  },
  "HTMLTimeElement": {
    "kind": "f",
    "props": {
      "prototype": {
        "props": {
          "datetime": {
            "kind": "v",
            "type": "String",
            "menu": "datetime : String"
          }
        },
        "class": "HTMLTimeElement",
        "type": "Object",
        "kind": "v"
      }
    }
  },
  "CharacterData": {
    "kind": "f",
    "props": {
      "prototype": {
        "props": {
          "substringData": {
            "kind": "f",
            "type": "String",
            "menu": "substringData(offset : Number, count : Number) : String"
          },
          "replaceData": {
            "kind": "f",
            "type": "undefined",
            "menu": "replaceData(offset : Number, count : Number, data : String) : undefined"
          },
          "remove": {
            "kind": "f",
            "type": "undefined",
            "menu": "remove() : undefined"
          },
          "insertData": {
            "kind": "f",
            "type": "undefined",
            "menu": "insertData(offset : Number, data : String) : undefined"
          },
          "deleteData": {
            "kind": "f",
            "type": "undefined",
            "menu": "deleteData(offset : Number, count : Number) : undefined"
          },
          "appendData": {
            "kind": "f",
            "type": "undefined",
            "menu": "appendData(data : String) : undefined"
          },
          "length": {
            "kind": "v",
            "type": "Number",
            "menu": "length : Number readonly"
          },
          "data": {
            "kind": "v",
            "type": "String",
            "menu": "data : String"
          }
        },
        "class": "CharacterData",
        "type": "Object",
        "kind": "v"
      }
    }
  },
  "HTMLPreElement": {
    "kind": "v"
  },
  "HTMLElement": {
    "kind": "f",
    "props": {
      "prototype": {
        "props": {
          "blur": {
            "kind": "f",
            "type": "undefined",
            "menu": "blur() : undefined"
          },
          "title": {
            "kind": "v",
            "type": "String",
            "menu": "title : String"
          },
          "dir": {
            "kind": "v",
            "type": "String",
            "menu": "dir : String"
          },
          "draggable": {
            "kind": "v",
            "type": "Boolean",
            "menu": "draggable : Boolean"
          },
          "dropzone": {
            "kind": "v",
            "type": "DOMSettableTokenList",
            "menu": "dropzone : DOMSettableTokenList readonly"
          },
          "hidden": {
            "kind": "v",
            "type": "Boolean",
            "menu": "hidden : Boolean"
          },
          "insertAdjacentHTML": {
            "kind": "f",
            "type": "undefined",
            "menu": "insertAdjacentHTML(position : String, html : String) : undefined"
          },
          "scrollIntoView": {
            "kind": "f",
            "type": "undefined",
            "menu": "scrollIntoView([top = false : Boolean]) : undefined"
          },
          "commandType": {
            "kind": "v",
            "type": "String",
            "menu": "commandType : String readonly"
          },
          "commandLabel": {
            "kind": "v",
            "type": "String",
            "menu": "commandLabel : String readonly"
          },
          "focus": {
            "kind": "f",
            "type": "undefined",
            "menu": "focus() : undefined"
          },
          "click": {
            "kind": "f",
            "type": "undefined",
            "menu": "click() : undefined"
          },
          "commandDisabled": {
            "kind": "v",
            "type": "Boolean",
            "menu": "commandDisabled : Boolean readonly"
          },
          "commandChecked": {
            "kind": "v",
            "type": "Boolean",
            "menu": "commandChecked : Boolean readonly"
          },
          "className": {
            "kind": "v",
            "type": "String",
            "menu": "className : String"
          },
          "classList": {
            "kind": "v",
            "type": "DOMTokenList",
            "menu": "classList : DOMTokenList readonly"
          },
          "accessKeyLabel": {
            "kind": "v",
            "type": "String",
            "menu": "accessKeyLabel : String readonly"
          },
          "accessKey": {
            "kind": "v",
            "type": "String",
            "menu": "accessKey : String"
          },
          "contextMenu": {
            "kind": "v",
            "type": "HTMLMenuElement",
            "menu": "contextMenu : HTMLMenuElement"
          },
          "contentEditable": {
            "kind": "v",
            "type": "String",
            "menu": "contentEditable : String"
          },
          "commandHidden": {
            "kind": "v",
            "type": "Boolean",
            "menu": "commandHidden : Boolean readonly"
          },
          "commandIcon": {
            "kind": "v",
            "type": "String",
            "menu": "commandIcon : String readonly"
          },
          "innerHTML": {
            "kind": "v",
            "type": "String",
            "menu": "innerHTML : String"
          },
          "isContentEditable": {
            "kind": "v",
            "type": "Boolean",
            "menu": "isContentEditable : Boolean readonly"
          },
          "lang": {
            "kind": "v",
            "type": "String",
            "menu": "lang : String"
          },
          "offsetHeight": {
            "kind": "v",
            "type": "Number",
            "menu": "offsetHeight : Number readonly"
          },
          "offsetLeft": {
            "kind": "v",
            "type": "Number",
            "menu": "offsetLeft : Number readonly"
          },
          "offsetParent": {
            "kind": "v",
            "type": "Element",
            "menu": "offsetParent : Element readonly"
          },
          "offsetTop": {
            "kind": "v",
            "type": "Number",
            "menu": "offsetTop : Number readonly"
          },
          "offsetWidth": {
            "kind": "v",
            "type": "Number",
            "menu": "offsetWidth : Number readonly"
          },
          "outerHTML": {
            "kind": "v",
            "type": "String",
            "menu": "outerHTML : String"
          },
          "spellcheck": {
            "kind": "v",
            "type": "Boolean",
            "menu": "spellcheck : Boolean"
          },
          "style": {
            "kind": "v",
            "type": "CSSStyleDeclaration",
            "menu": "style : CSSStyleDeclaration readonly"
          },
          "tabIndex": {
            "kind": "v",
            "type": "Number",
            "menu": "tabIndex : Number"
          }
        },
        "class": "HTMLElement",
        "type": "Object",
        "kind": "v"
      }
    }
  },
  "HTMLDivElement": {
    "kind": "v"
  },
  "Comment": {
    "kind": "v"
  }
}
